{
	"singerList": {
		"data": {
			"area": -100,
			"genre": -100,
			"index": -100,
			"sex": -100,
			"singerlist": [{
				"country": "内地",
				"singer_id": 1199300,
				"singer_mid": "0013RsPD3Xs0FG",
				"singer_name": "半阳",
				"singer_pic": "http://y.gtimg.cn/music/photo_new/T001R150x150M0000013RsPD3Xs0FG.webp"
			}, {
				"country": "内地",
				"singer_id": 5062,
				"singer_mid": "002J4UUk29y8BY",
				"singer_name": "薛之谦",
				"singer_pic": "http://y.gtimg.cn/music/photo_new/T001R150x150M000002J4UUk29y8BY.webp"
			}, {
				"country": "香港",
				"singer_id": 13948,
				"singer_mid": "001fNHEf1SFEFN",
				"singer_name": "G.E.M. 邓紫棋",
				"singer_pic": "http://y.gtimg.cn/music/photo_new/T001R150x150M000001fNHEf1SFEFN.webp"
			}, {
				"country": "台湾",
				"singer_id": 4558,
				"singer_mid": "0025NhlN2yWrP4",
				"singer_name": "周杰伦",
				"singer_pic": "http://y.gtimg.cn/music/photo_new/T001R150x150M0000025NhlN2yWrP4.webp"
			}, {
				"country": "新加坡",
				"singer_id": 4286,
				"singer_mid": "001BLpXF2DyJe2",
				"singer_name": "林俊杰",
				"singer_pic": "http://y.gtimg.cn/music/photo_new/T001R150x150M000001BLpXF2DyJe2.webp"
			}, {
				"country": "内地",
				"singer_id": 60505,
				"singer_mid": "000aHmbL2aPXWH",
				"singer_name": "李荣浩",
				"singer_pic": "http://y.gtimg.cn/music/photo_new/T001R150x150M000000aHmbL2aPXWH.webp"
			}, {
				"country": "内地",
				"singer_id": 24833,
				"singer_mid": "002mze3U0NYXOM",
				"singer_name": "胡夏",
				"singer_pic": "http://y.gtimg.cn/music/photo_new/T001R150x150M000002mze3U0NYXOM.webp"
			}, {
				"country": "英国",
				"singer_id": 944940,
				"singer_mid": "0020PeOh4ZaCw1",
				"singer_name": "Alan Walker (艾伦·沃克)",
				"singer_pic": "http://y.gtimg.cn/music/photo_new/T001R150x150M0000020PeOh4ZaCw1.webp"
			}, {
				"country": "内地",
				"singer_id": 1507534,
				"singer_mid": "001BHDR33FZVZ0",
				"singer_name": "毛不易",
				"singer_pic": "http://y.gtimg.cn/music/photo_new/T001R150x150M000001BHDR33FZVZ0.webp"
			}, {
				"country": "内地",
				"singer_id": 867,
				"singer_mid": "001s4BJ92fSpPu",
				"singer_name": "贺一航",
				"singer_pic": "http://y.gtimg.cn/music/photo_new/T001R150x150M000001s4BJ92fSpPu.webp"
			}, {
				"country": "香港",
				"singer_id": 143,
				"singer_mid": "003Nz2So3XXYek",
				"singer_name": "陈奕迅",
				"singer_pic": "http://y.gtimg.cn/music/photo_new/T001R150x150M000003Nz2So3XXYek.webp"
			}, {
				"country": "内地",
				"singer_id": 19329,
				"singer_mid": "000Qm9wO1bcM6J",
				"singer_name": "李玉刚",
				"singer_pic": "http://y.gtimg.cn/music/photo_new/T001R150x150M000000Qm9wO1bcM6J.webp"
			}, {
				"country": "内地",
				"singer_id": 89698,
				"singer_mid": "003Cn3Yh16q1MO",
				"singer_name": "庄心妍",
				"singer_pic": "http://y.gtimg.cn/music/photo_new/T001R150x150M000003Cn3Yh16q1MO.webp"
			}, {
				"country": "内地",
				"singer_id": 67008,
				"singer_mid": "000poF8D027tPr",
				"singer_name": "于文文",
				"singer_pic": "http://y.gtimg.cn/music/photo_new/T001R150x150M000000poF8D027tPr.webp"
			}, {
				"country": "内地",
				"singer_id": 1103924,
				"singer_mid": "001ZVMXf3ZYVX7",
				"singer_name": "曲肖冰",
				"singer_pic": "http://y.gtimg.cn/music/photo_new/T001R150x150M000001ZVMXf3ZYVX7.webp"
			}, {
				"country": "内地",
				"singer_id": 2079450,
				"singer_mid": "000wHoyF0OZB6B",
				"singer_name": "胡66",
				"singer_pic": "http://y.gtimg.cn/music/photo_new/T001R150x150M000000wHoyF0OZB6B.webp"
			}, {
				"country": "内地",
				"singer_id": 963482,
				"singer_mid": "004GZcGF2ZgJYo",
				"singer_name": "白小白",
				"singer_pic": "http://y.gtimg.cn/music/photo_new/T001R150x150M000004GZcGF2ZgJYo.webp"
			}, {
				"country": "内地",
				"singer_id": 7221,
				"singer_mid": "000CK5xN3yZDJt",
				"singer_name": "许嵩",
				"singer_pic": "http://y.gtimg.cn/music/photo_new/T001R150x150M000000CK5xN3yZDJt.webp"
			}, {
				"country": "内地",
				"singer_id": 940748,
				"singer_mid": "004WgCsE3KBddt",
				"singer_name": "陈粒",
				"singer_pic": "http://y.gtimg.cn/music/photo_new/T001R150x150M000004WgCsE3KBddt.webp"
			}, {
				"country": "内地",
				"singer_id": 4607,
				"singer_mid": "000aw4WC2EQYTv",
				"singer_name": "张靓颖",
				"singer_pic": "http://y.gtimg.cn/music/photo_new/T001R150x150M000000aw4WC2EQYTv.webp"
			}, {
				"country": "内地",
				"singer_id": 31035,
				"singer_mid": "003U6coz1AhN3H",
				"singer_name": "简弘亦",
				"singer_pic": "http://y.gtimg.cn/music/photo_new/T001R150x150M000003U6coz1AhN3H.webp"
			}, {
				"country": "美国",
				"singer_id": 265,
				"singer_mid": "001JDzPT3JdvqK",
				"singer_name": "王力宏",
				"singer_pic": "http://y.gtimg.cn/music/photo_new/T001R150x150M000001JDzPT3JdvqK.webp"
			}, {
				"country": "美国",
				"singer_id": 43197,
				"singer_mid": "0046fVNz3ruk2r",
				"singer_name": "Selena Gomez (赛琳娜·戈麦斯)",
				"singer_pic": "http://y.gtimg.cn/music/photo_new/T001R150x150M0000046fVNz3ruk2r.webp"
			}, {
				"country": "内地",
				"singer_id": 4588,
				"singer_mid": "001C0c6j1VyLfh",
				"singer_name": "黑龙",
				"singer_pic": "http://y.gtimg.cn/music/photo_new/T001R150x150M000001C0c6j1VyLfh.webp"
			}, {
				"country": "新加坡",
				"singer_id": 112,
				"singer_mid": "000hNnWC3kko2c",
				"singer_name": "蔡健雅",
				"singer_pic": "http://y.gtimg.cn/music/photo_new/T001R150x150M000000hNnWC3kko2c.webp"
			}, {
				"country": "内地",
				"singer_id": 6499,
				"singer_mid": "002azErJ0UcDN6",
				"singer_name": "张杰",
				"singer_pic": "http://y.gtimg.cn/music/photo_new/T001R150x150M000002azErJ0UcDN6.webp"
			}, {
				"country": "内地",
				"singer_id": 4615,
				"singer_mid": "002ZOuVm3Qn20Y",
				"singer_name": "李宇春",
				"singer_pic": "http://y.gtimg.cn/music/photo_new/T001R150x150M000002ZOuVm3Qn20Y.webp"
			}, {
				"country": "美国",
				"singer_id": 156095,
				"singer_mid": "004ABIFV1EZUAj",
				"singer_name": "The Chainsmokers (烟鬼组合)",
				"singer_pic": "http://y.gtimg.cn/music/photo_new/T001R150x150M000004ABIFV1EZUAj.webp"
			}, {
				"country": "台湾",
				"singer_id": 11608,
				"singer_mid": "003tMm0y0TuewY",
				"singer_name": "杨宗纬",
				"singer_pic": "http://y.gtimg.cn/music/photo_new/T001R150x150M000003tMm0y0TuewY.webp"
			}, {
				"country": "韩国",
				"singer_id": 11733,
				"singer_mid": "004AlfUb0cVkN1",
				"singer_name": "BIGBANG (빅뱅)",
				"singer_pic": "http://y.gtimg.cn/music/photo_new/T001R150x150M000004AlfUb0cVkN1.webp"
			}, {
				"country": "内地",
				"singer_id": 198135,
				"singer_mid": "001IoTZp19YMDG",
				"singer_name": "易烊千玺",
				"singer_pic": "http://y.gtimg.cn/music/photo_new/T001R150x150M000001IoTZp19YMDG.webp"
			}, {
				"country": "内地",
				"singer_id": 15514,
				"singer_mid": "001Yxpxc0OaUUX",
				"singer_name": "逃跑计划",
				"singer_pic": "http://y.gtimg.cn/music/photo_new/T001R150x150M000001Yxpxc0OaUUX.webp"
			}, {
				"country": "香港",
				"singer_id": 2,
				"singer_mid": "002pUZT93gF4Cu",
				"singer_name": "BEYOND",
				"singer_pic": "http://y.gtimg.cn/music/photo_new/T001R150x150M000002pUZT93gF4Cu.webp"
			}, {
				"country": "香港",
				"singer_id": 163,
				"singer_mid": "003aQYLo2x8izP",
				"singer_name": "刘德华",
				"singer_pic": "http://y.gtimg.cn/music/photo_new/T001R150x150M000003aQYLo2x8izP.webp"
			}, {
				"country": "内地",
				"singer_id": 1327483,
				"singer_mid": "000985uR2CKS2P",
				"singer_name": "艾辰",
				"singer_pic": "http://y.gtimg.cn/music/photo_new/T001R150x150M000000985uR2CKS2P.webp"
			}, {
				"country": "台湾",
				"singer_id": 6028,
				"singer_mid": "003ArN8Z0WpjTz",
				"singer_name": "A-Lin",
				"singer_pic": "http://y.gtimg.cn/music/photo_new/T001R150x150M000003ArN8Z0WpjTz.webp"
			}, {
				"country": "内地",
				"singer_id": 163550,
				"singer_mid": "002Vcz8F2hpBQj",
				"singer_name": "华晨宇",
				"singer_pic": "http://y.gtimg.cn/music/photo_new/T001R150x150M000002Vcz8F2hpBQj.webp"
			}, {
				"country": "内地",
				"singer_id": 1398057,
				"singer_mid": "004Hxj1m48xwGi",
				"singer_name": "广东雨神",
				"singer_pic": "http://y.gtimg.cn/music/photo_new/T001R150x150M000004Hxj1m48xwGi.webp"
			}, {
				"country": "内地",
				"singer_id": 1233588,
				"singer_mid": "001yMNFV23daTV",
				"singer_name": "冯提莫",
				"singer_pic": "http://y.gtimg.cn/music/photo_new/T001R150x150M000001yMNFV23daTV.webp"
			}, {
				"country": "内地",
				"singer_id": 4418,
				"singer_mid": "0002ankM4d5yZI",
				"singer_name": "郭顶",
				"singer_pic": "http://y.gtimg.cn/music/photo_new/T001R150x150M0000002ankM4d5yZI.webp"
			}, {
				"country": "内地",
				"singer_id": 34412,
				"singer_mid": "000zmpju02bEBm",
				"singer_name": "TFBOYS",
				"singer_pic": "http://y.gtimg.cn/music/photo_new/T001R150x150M000000zmpju02bEBm.webp"
			}, {
				"country": "内地",
				"singer_id": 40449,
				"singer_mid": "001Lr98T0yEWAk",
				"singer_name": "赵雷",
				"singer_pic": "http://y.gtimg.cn/music/photo_new/T001R150x150M000001Lr98T0yEWAk.webp"
			}, {
				"country": "英国",
				"singer_id": 22785,
				"singer_mid": "001RRlcX2n2NLs",
				"singer_name": "Olly Murs (奥利·莫尔斯)",
				"singer_pic": "http://y.gtimg.cn/music/photo_new/T001R150x150M000001RRlcX2n2NLs.webp"
			}, {
				"country": "内地",
				"singer_id": 1060995,
				"singer_mid": "003NTUrM17PJhv",
				"singer_name": "徐秉龙",
				"singer_pic": "http://y.gtimg.cn/music/photo_new/T001R150x150M000003NTUrM17PJhv.webp"
			}, {
				"country": "内地",
				"singer_id": 4610,
				"singer_mid": "004HlS192u9J5g",
				"singer_name": "周笔畅",
				"singer_pic": "http://y.gtimg.cn/music/photo_new/T001R150x150M000004HlS192u9J5g.webp"
			}, {
				"country": "内地",
				"singer_id": 178612,
				"singer_mid": "004OFF5J1uCT1c",
				"singer_name": "金玟岐",
				"singer_pic": "http://y.gtimg.cn/music/photo_new/T001R150x150M000004OFF5J1uCT1c.webp"
			}, {
				"country": "美国",
				"singer_id": 39000,
				"singer_mid": "000jnR7q3pCzYG",
				"singer_name": "Charlie Puth (查理·普斯)",
				"singer_pic": "http://y.gtimg.cn/music/photo_new/T001R150x150M000000jnR7q3pCzYG.webp"
			}, {
				"country": "内地",
				"singer_id": 1005787,
				"singer_mid": "001KH1tJ02U8KY",
				"singer_name": "摩登兄弟",
				"singer_pic": "http://y.gtimg.cn/music/photo_new/T001R150x150M000001KH1tJ02U8KY.webp"
			}, {
				"country": "内地",
				"singer_id": 2169599,
				"singer_mid": "000Rh4DK4MmxIU",
				"singer_name": "火箭少女101",
				"singer_pic": "http://y.gtimg.cn/music/photo_new/T001R150x150M000000Rh4DK4MmxIU.webp"
			}, {
				"country": "内地",
				"singer_id": 199509,
				"singer_mid": "003fA5G40k6hKc",
				"singer_name": "周深",
				"singer_pic": "http://y.gtimg.cn/music/photo_new/T001R150x150M000003fA5G40k6hKc.webp"
			}, {
				"country": "",
				"singer_id": 8061,
				"singer_mid": "002DYd0J2HmOvc",
				"singer_name": "儿歌",
				"singer_pic": "http://y.gtimg.cn/music/photo_new/T001R150x150M000002DYd0J2HmOvc.webp"
			}, {
				"country": "内地",
				"singer_id": 120,
				"singer_mid": "0043OO7j3TsLnO",
				"singer_name": "杨坤",
				"singer_pic": "http://y.gtimg.cn/music/photo_new/T001R150x150M0000043OO7j3TsLnO.webp"
			}, {
				"country": "内地",
				"singer_id": 33625,
				"singer_mid": "001ii8ME2uOv92",
				"singer_name": "蒋家驹（蒋蒋）",
				"singer_pic": "http://y.gtimg.cn/music/photo_new/T001R150x150M000001ii8ME2uOv92.webp"
			}, {
				"country": "香港",
				"singer_id": 174,
				"singer_mid": "004Be55m1SJaLk",
				"singer_name": "张学友",
				"singer_pic": "http://y.gtimg.cn/music/photo_new/T001R150x150M000004Be55m1SJaLk.webp"
			}, {
				"country": "台湾",
				"singer_id": 227,
				"singer_mid": "0027pdHE4STooO",
				"singer_name": "蔡依林",
				"singer_pic": "http://y.gtimg.cn/music/photo_new/T001R150x150M0000027pdHE4STooO.webp"
			}, {
				"country": "台湾",
				"singer_id": 168,
				"singer_mid": "0044wQXL0ElWF1",
				"singer_name": "张宇",
				"singer_pic": "http://y.gtimg.cn/music/photo_new/T001R150x150M0000044wQXL0ElWF1.webp"
			}, {
				"country": "",
				"singer_id": 173914,
				"singer_mid": "003AD17D4PYPFR",
				"singer_name": "Vicetone (副音乐团)",
				"singer_pic": "http://y.gtimg.cn/music/photo_new/T001R150x150M000003AD17D4PYPFR.webp"
			}, {
				"country": "台湾",
				"singer_id": 224,
				"singer_mid": "002raUWw3PXdkT",
				"singer_name": "张韶涵",
				"singer_pic": "http://y.gtimg.cn/music/photo_new/T001R150x150M000002raUWw3PXdkT.webp"
			}, {
				"country": "内地",
				"singer_id": 1473880,
				"singer_mid": "004V53Ga0bV65j",
				"singer_name": "陈雪凝",
				"singer_pic": "http://y.gtimg.cn/music/photo_new/T001R150x150M000004V53Ga0bV65j.webp"
			}, {
				"country": "内地",
				"singer_id": 12111,
				"singer_mid": "004YXxql1sSr2o",
				"singer_name": "金志文",
				"singer_pic": "http://y.gtimg.cn/music/photo_new/T001R150x150M000004YXxql1sSr2o.webp"
			}, {
				"country": "内地",
				"singer_id": 188132,
				"singer_mid": "0020uUft0MjWjW",
				"singer_name": "刘珂矣",
				"singer_pic": "http://y.gtimg.cn/music/photo_new/T001R150x150M0000020uUft0MjWjW.webp"
			}, {
				"country": "台湾",
				"singer_id": 245,
				"singer_mid": "0010PLKl2Wgolz",
				"singer_name": "飞儿乐团",
				"singer_pic": "http://y.gtimg.cn/music/photo_new/T001R150x150M0000010PLKl2Wgolz.webp"
			}, {
				"country": "内地",
				"singer_id": 161301,
				"singer_mid": "000IBYF50SRnXP",
				"singer_name": "王源",
				"singer_pic": "http://y.gtimg.cn/music/photo_new/T001R150x150M000000IBYF50SRnXP.webp"
			}, {
				"country": "内地",
				"singer_id": 3954,
				"singer_mid": "001z2JmX09LLgL",
				"singer_name": "汪苏泷",
				"singer_pic": "http://y.gtimg.cn/music/photo_new/T001R150x150M000001z2JmX09LLgL.webp"
			}, {
				"country": "内地",
				"singer_id": 36691,
				"singer_mid": "00472DR10Ytv83",
				"singer_name": "袁娅维",
				"singer_pic": "http://y.gtimg.cn/music/photo_new/T001R150x150M00000472DR10Ytv83.webp"
			}, {
				"country": "内地",
				"singer_id": 4419,
				"singer_mid": "003WlPvN2EvRaj",
				"singer_name": "韩红",
				"singer_pic": "http://y.gtimg.cn/music/photo_new/T001R150x150M000003WlPvN2EvRaj.webp"
			}, {
				"country": "内地",
				"singer_id": 1288409,
				"singer_mid": "002vALgR3hRRlv",
				"singer_name": "音阙诗听",
				"singer_pic": "http://y.gtimg.cn/music/photo_new/T001R150x150M000002vALgR3hRRlv.webp"
			}, {
				"country": "内地",
				"singer_id": 1043567,
				"singer_mid": "004QoDUs3jfOC6",
				"singer_name": "韩安旭",
				"singer_pic": "http://y.gtimg.cn/music/photo_new/T001R150x150M000004QoDUs3jfOC6.webp"
			}, {
				"country": "香港",
				"singer_id": 54,
				"singer_mid": "000cISVf2QqLc6",
				"singer_name": "莫文蔚",
				"singer_pic": "http://y.gtimg.cn/music/photo_new/T001R150x150M000000cISVf2QqLc6.webp"
			}, {
				"country": "内地",
				"singer_id": 951320,
				"singer_mid": "000PeZCQ1i4XVs",
				"singer_name": "房东的猫",
				"singer_pic": "http://y.gtimg.cn/music/photo_new/T001R150x150M000000PeZCQ1i4XVs.webp"
			}, {
				"country": "澳大利亚",
				"singer_id": 7015,
				"singer_mid": "004ItgA32BhfdC",
				"singer_name": "Sia (希雅)",
				"singer_pic": "http://y.gtimg.cn/music/photo_new/T001R150x150M000004ItgA32BhfdC.webp"
			}, {
				"country": "英国",
				"singer_id": 29222,
				"singer_mid": "0045p4Sz0LIwL5",
				"singer_name": "Ed Sheeran (艾德·希兰)",
				"singer_pic": "http://y.gtimg.cn/music/photo_new/T001R150x150M0000045p4Sz0LIwL5.webp"
			}, {
				"country": "台湾",
				"singer_id": 74,
				"singer_mid": "000Sp0Bz4JXH0o",
				"singer_name": "五月天",
				"singer_pic": "http://y.gtimg.cn/music/photo_new/T001R150x150M000000Sp0Bz4JXH0o.webp"
			}, {
				"country": "内地",
				"singer_id": 204664,
				"singer_mid": "001SqkF53OEhdO",
				"singer_name": "鹿晗",
				"singer_pic": "http://y.gtimg.cn/music/photo_new/T001R150x150M000001SqkF53OEhdO.webp"
			}, {
				"country": "加拿大",
				"singer_id": 16257,
				"singer_mid": "002DYpxl3hW3EP",
				"singer_name": "Justin Bieber (贾斯汀·比伯)",
				"singer_pic": "http://y.gtimg.cn/music/photo_new/T001R150x150M000002DYpxl3hW3EP.webp"
			}, {
				"country": "英国",
				"singer_id": 4984,
				"singer_mid": "000ORrN70zDZX8",
				"singer_name": "Craig David (克雷格·大卫)",
				"singer_pic": "http://y.gtimg.cn/music/photo_new/T001R150x150M000000ORrN70zDZX8.webp"
			}, {
				"country": "韩国",
				"singer_id": 5233,
				"singer_mid": "001FheYB4aB9aU",
				"singer_name": "휘성 (辉星)",
				"singer_pic": "http://y.gtimg.cn/music/photo_new/T001R150x150M000001FheYB4aB9aU.webp"
			}, {
				"country": "爱尔兰",
				"singer_id": 4404,
				"singer_mid": "002uNtOf2Xj5eB",
				"singer_name": "Westlife (西城男孩)",
				"singer_pic": "http://y.gtimg.cn/music/photo_new/T001R150x150M000002uNtOf2Xj5eB.webp"
			}, {
				"country": "内地",
				"singer_id": 244,
				"singer_mid": "000iZroE1VWLJG",
				"singer_name": "刀郎",
				"singer_pic": "http://y.gtimg.cn/music/photo_new/T001R150x150M000000iZroE1VWLJG.webp"
			}, {
				"country": "内地",
				"singer_id": 14411,
				"singer_mid": "004dXznj3zlHKW",
				"singer_name": "孙露",
				"singer_pic": "http://y.gtimg.cn/music/photo_new/T001R150x150M000004dXznj3zlHKW.webp"
			}],
			"tags": {
				"area": [{
					"id": -100,
					"name": "全部"
				}, {
					"id": 200,
					"name": "内地"
				}, {
					"id": 2,
					"name": "港台"
				}, {
					"id": 5,
					"name": "欧美"
				}, {
					"id": 4,
					"name": "日本"
				}, {
					"id": 3,
					"name": "韩国"
				}, {
					"id": 6,
					"name": "其他"
				}],
				"genre": [{
					"id": -100,
					"name": "全部"
				}, {
					"id": 1,
					"name": "流行"
				}, {
					"id": 6,
					"name": "嘻哈"
				}, {
					"id": 2,
					"name": "摇滚"
				}, {
					"id": 4,
					"name": "电子"
				}, {
					"id": 3,
					"name": "民谣"
				}, {
					"id": 8,
					"name": "R&B"
				}, {
					"id": 10,
					"name": "民歌"
				}, {
					"id": 9,
					"name": "轻音乐"
				}, {
					"id": 5,
					"name": "爵士"
				}, {
					"id": 14,
					"name": "古典"
				}, {
					"id": 25,
					"name": "乡村"
				}, {
					"id": 20,
					"name": "蓝调"
				}],
				"index": [{
					"id": -100,
					"name": "热门"
				}, {
					"id": 1,
					"name": "A"
				}, {
					"id": 2,
					"name": "B"
				}, {
					"id": 3,
					"name": "C"
				}, {
					"id": 4,
					"name": "D"
				}, {
					"id": 5,
					"name": "E"
				}, {
					"id": 6,
					"name": "F"
				}, {
					"id": 7,
					"name": "G"
				}, {
					"id": 8,
					"name": "H"
				}, {
					"id": 9,
					"name": "I"
				}, {
					"id": 10,
					"name": "J"
				}, {
					"id": 11,
					"name": "K"
				}, {
					"id": 12,
					"name": "L"
				}, {
					"id": 13,
					"name": "M"
				}, {
					"id": 14,
					"name": "N"
				}, {
					"id": 15,
					"name": "O"
				}, {
					"id": 16,
					"name": "P"
				}, {
					"id": 17,
					"name": "Q"
				}, {
					"id": 18,
					"name": "R"
				}, {
					"id": 19,
					"name": "S"
				}, {
					"id": 20,
					"name": "T"
				}, {
					"id": 21,
					"name": "U"
				}, {
					"id": 22,
					"name": "V"
				}, {
					"id": 23,
					"name": "W"
				}, {
					"id": 24,
					"name": "X"
				}, {
					"id": 25,
					"name": "Y"
				}, {
					"id": 26,
					"name": "Z"
				}, {
					"id": 27,
					"name": "#"
				}],
				"sex": [{
					"id": -100,
					"name": "全部"
				}, {
					"id": 0,
					"name": "男"
				}, {
					"id": 1,
					"name": "女"
				}, {
					"id": 2,
					"name": "组合"
				}]
			},
			"total": 23706
		},
		"code": 0
	},
	"code": 0,
	"ts": 1548853111916
}